blockchain_todo/__init__.py
blockchain_todo/app.py
blockchain_todo-1.0.dist-info/METADATA
blockchain_todo-1.0.dist-info/WHEEL
blockchain_todo-1.0.dist-info/entry_points.txt
blockchain_todo-1.0.dist-info/licenses/LICENSE
blockchain_todo-1.0.dist-info/RECORD
