Metadata-Version: 2.1
Name: blockchain_todo
Version: 1.0
Summary: A Blockchain Supported To Do List
Project-URL: Home-page, https://github.com/crillerium/
Author-email: Crillerium <crillerium@outlook.com>
License-File: LICENSE
Classifier: License :: OSI Approved :: MIT License
Classifier: Operating System :: OS Independent
Classifier: Programming Language :: Python :: 3
Requires-Python: >=3.7
Requires-Dist: fire
Requires-Dist: loongchain
